{
  "hash": "61c6313d",
  "browserHash": "391ac117",
  "optimized": {
    "react": {
      "src": "../../node_modules/react/index.js",
      "file": "react.js",
      "fileHash": "5b0d63d6",
      "needsInterop": true
    },
    "react/jsx-dev-runtime": {
      "src": "../../node_modules/react/jsx-dev-runtime.js",
      "file": "react_jsx-dev-runtime.js",
      "fileHash": "9a132c20",
      "needsInterop": true
    },
    "react/jsx-runtime": {
      "src": "../../node_modules/react/jsx-runtime.js",
      "file": "react_jsx-runtime.js",
      "fileHash": "ce1c0156",
      "needsInterop": true
    },
    "axios": {
      "src": "../../node_modules/axios/index.js",
      "file": "axios.js",
      "fileHash": "28d3ee12",
      "needsInterop": false
    },
    "clsx": {
      "src": "../../node_modules/clsx/dist/clsx.mjs",
      "file": "clsx.js",
      "fileHash": "49d9bfb7",
      "needsInterop": false
    },
    "lucide-react": {
      "src": "../../node_modules/lucide-react/dist/esm/lucide-react.js",
      "file": "lucide-react.js",
      "fileHash": "46d6f933",
      "needsInterop": false
    },
    "react-dom/client": {
      "src": "../../node_modules/react-dom/client.js",
      "file": "react-dom_client.js",
      "fileHash": "063a33bf",
      "needsInterop": true
    }
  },
  "chunks": {
    "chunk-SEVHLZHR": {
      "file": "chunk-SEVHLZHR.js"
    },
    "chunk-ZS7NZCD4": {
      "file": "chunk-ZS7NZCD4.js"
    }
  }
}